modern_slavery_statements_research/__init__.py
modern_slavery_statements_research/download_corpus.py
modern_slavery_statements_research-0.3.0.dist-info/LICENSE
modern_slavery_statements_research-0.3.0.dist-info/METADATA
modern_slavery_statements_research-0.3.0.dist-info/WHEEL
modern_slavery_statements_research-0.3.0.dist-info/entry_points.txt
modern_slavery_statements_research-0.3.0.dist-info/top_level.txt
modern_slavery_statements_research-0.3.0.dist-info/RECORD
