Metadata-Version: 2.1
Name: modern-slavery-statements-research
Version: 0.3.0
Summary: A collection of tools to conduct research on the Modern Slavery Statements text corpus.
Home-page: https://github.com/the-future-society/modern-slavery-statements-research/
Author: The Future Society
Author-email: edgar@bravetech.io
License: MIT
Platform: UNKNOWN
Classifier: License :: OSI Approved :: MIT License
Classifier: Programming Language :: Python
Classifier: Programming Language :: Python :: 3
Classifier: Programming Language :: Python :: 3.6
Classifier: Programming Language :: Python :: Implementation :: PyPy
Classifier: Development Status :: 3 - Alpha
Classifier: Intended Audience :: Developers
Requires-Python: >=3.6.0
Requires-Dist: boto3
